AMD/AMD.py
AMD/__init__.py
AMD-2.6.dist-info/LICENSE.txt
AMD-2.6.dist-info/METADATA
AMD-2.6.dist-info/WHEEL
AMD-2.6.dist-info/top_level.txt
AMD-2.6.dist-info/RECORD
